{
  "kind": "youtube#videoListResponse",
  "etag": "aoky9BHobHGzEEl_U6WomerMees",
  "items": [
    {
      "kind": "youtube#video",
      "etag": "_k3XzOjzpMcxd-PJKpC-bFd9u8Y",
      "id": "F6PqxbvOCUI",
      "snippet": {
        "publishedAt": "2024-05-11T16:00:00Z",
        "channelId": "UCX6OQ3DkcsbYNE6H8uQQuVA",
        "title": "Protect The Yacht, Keep It!",
        "description": "This video did not go how I expected it to\nCraft your perfect defense from a combination of powerful Monkey Towers and awesome Heroes, then pop every last invading Bloon! Grab your copy of Bloons TD 6 now - https://ninja.kiwi/mrbeast\n\nPlay the Official Fortnite Creative Map For This Video Here:\nMrBeast Bed Wars 🛌 - 5948-5884-5269\nhttps://www.fortnite.com/@mrbeast/5948-5884-5269\n\nNew Merch - https://mrbeast.store\n\nCheck out Viewstats! - https://www.viewstats.com/\n\nSUBSCRIBE OR I TAKE YOUR DOG\n╔═╦╗╔╦╗╔═╦═╦╦╦╦╗╔═╗\n║╚╣║║║╚╣╚╣╔╣╔╣║╚╣═╣ \n╠╗║╚╝║║╠╗║╚╣║║║║║═╣\n╚═╩══╩═╩═╩═╩╝╚╩═╩═╝\n\nFor any questions or inquiries regarding this video, please reach out to chucky@mrbeastbusiness.com\n\nMusic Provided by https://www.extrememusic.com\n\n----------------------------------------------------------------\nfollow all of these or i will kick you\n• Facebook - https://www.facebook.com/MrBeast6000/\n• Twitter - https://twitter.com/MrBeast\n•  Instagram - https://www.instagram.com/mrbeast\n•  Im Hiring! - https://www.mrbeastjobs.com/\n--------------------------------------------------------------------",
        "thumbnails": {
          "default": {
            "url": "https://i.ytimg.com/vi/F6PqxbvOCUI/default.jpg",
            "width": 120,
            "height": 90
          },
          "medium": {
            "url": "https://i.ytimg.com/vi/F6PqxbvOCUI/mqdefault.jpg",
            "width": 320,
            "height": 180
          },
          "high": {
            "url": "https://i.ytimg.com/vi/F6PqxbvOCUI/hqdefault.jpg",
            "width": 480,
            "height": 360
          },
          "standard": {
            "url": "https://i.ytimg.com/vi/F6PqxbvOCUI/sddefault.jpg",
            "width": 640,
            "height": 480
          },
          "maxres": {
            "url": "https://i.ytimg.com/vi/F6PqxbvOCUI/maxresdefault.jpg",
            "width": 1280,
            "height": 720
          }
        },
        "channelTitle": "MrBeast",
        "categoryId": "24",
        "liveBroadcastContent": "none",
        "defaultLanguage": "en",
        "localized": {
          "title": "Protect The Yacht, Keep It!",
          "description": "This video did not go how I expected it to\nCraft your perfect defense from a combination of powerful Monkey Towers and awesome Heroes, then pop every last invading Bloon! Grab your copy of Bloons TD 6 now - https://ninja.kiwi/mrbeast\n\nPlay the Official Fortnite Creative Map For This Video Here:\nMrBeast Bed Wars 🛌 - 5948-5884-5269\nhttps://www.fortnite.com/@mrbeast/5948-5884-5269\n\nNew Merch - https://mrbeast.store\n\nCheck out Viewstats! - https://www.viewstats.com/\n\nSUBSCRIBE OR I TAKE YOUR DOG\n╔═╦╗╔╦╗╔═╦═╦╦╦╦╗╔═╗\n║╚╣║║║╚╣╚╣╔╣╔╣║╚╣═╣ \n╠╗║╚╝║║╠╗║╚╣║║║║║═╣\n╚═╩══╩═╩═╩═╩╝╚╩═╩═╝\n\nFor any questions or inquiries regarding this video, please reach out to chucky@mrbeastbusiness.com\n\nMusic Provided by https://www.extrememusic.com\n\n----------------------------------------------------------------\nfollow all of these or i will kick you\n• Facebook - https://www.facebook.com/MrBeast6000/\n• Twitter - https://twitter.com/MrBeast\n•  Instagram - https://www.instagram.com/mrbeast\n•  Im Hiring! - https://www.mrbeastjobs.com/\n--------------------------------------------------------------------"
        },
        "defaultAudioLanguage": "en"
      }
    },
    {
      "kind": "youtube#video",
      "etag": "PV-qk1L2Ek0nb9yNKX396EdK2nQ",
      "id": "vXsbxxNpeI0",
      "snippet": {
        "publishedAt": "2024-05-12T05:43:56Z",
        "channelId": "UCbzRzJNHx7ZLlJML9BjZQVQ",
        "title": "The Dominating SKILL From Vasiliy Lomachenko Against George Kambosos! | FIGHT HIGHLIGHTS",
        "description": "Watch the highlights from #vasiliylomachenko's dominating performance against the hometown hero George Kambosos in which Loma managed to stop George in the late rounds. #boxing #highlights\n\nSubscribe to our YouTube channel to get notified about the latest highlights, free full fights, and fight week content as it's posted.\n\nFollow Top Rank on X: http://www.twitter.com/trboxing\nFollow Top Rank on Instagram: http://www.instagram.com/toprank\nFollow Top Rank on TikTok: https://www.tiktok.com/@trboxing\nLike Top Rank on Facebook: http://www.facebook.com/trboxing",
        "thumbnails": {
          "default": {
            "url": "https://i.ytimg.com/vi/vXsbxxNpeI0/default.jpg",
            "width": 120,
            "height": 90
          },
          "medium": {
            "url": "https://i.ytimg.com/vi/vXsbxxNpeI0/mqdefault.jpg",
            "width": 320,
            "height": 180
          },
          "high": {
            "url": "https://i.ytimg.com/vi/vXsbxxNpeI0/hqdefault.jpg",
            "width": 480,
            "height": 360
          },
          "standard": {
            "url": "https://i.ytimg.com/vi/vXsbxxNpeI0/sddefault.jpg",
            "width": 640,
            "height": 480
          },
          "maxres": {
            "url": "https://i.ytimg.com/vi/vXsbxxNpeI0/maxresdefault.jpg",
            "width": 1280,
            "height": 720
          }
        },
        "channelTitle": "Top Rank Boxing",
        "tags": [
          "top rank boxing",
          "boxing",
          "vasiliy lomachenko vs george kambosos fight highlights",
          "vasiliy lomachenko vs george kambosos fight",
          "vasiliy lomachenko george kambosos",
          "vasiliy lomachenko boxing highlights",
          "vasiliy lomachenko vs george kambosos",
          "vasyl lomachenko",
          "vasyl lomachenko vs george kambosos",
          "vasyl lomachenko vs george kambosos fight",
          "vasiliy lomachenko vs george kambosos full fight",
          "vasiliy lomachenko",
          "loma vs kambosos highlights",
          "loma vs kambosos",
          "lomachenko vs kambosos",
          "loma"
        ],
        "categoryId": "17",
        "liveBroadcastContent": "none",
        "localized": {
          "title": "The Dominating SKILL From Vasiliy Lomachenko Against George Kambosos! | FIGHT HIGHLIGHTS",
          "description": "Watch the highlights from #vasiliylomachenko's dominating performance against the hometown hero George Kambosos in which Loma managed to stop George in the late rounds. #boxing #highlights\n\nSubscribe to our YouTube channel to get notified about the latest highlights, free full fights, and fight week content as it's posted.\n\nFollow Top Rank on X: http://www.twitter.com/trboxing\nFollow Top Rank on Instagram: http://www.instagram.com/toprank\nFollow Top Rank on TikTok: https://www.tiktok.com/@trboxing\nLike Top Rank on Facebook: http://www.facebook.com/trboxing"
        },
        "defaultAudioLanguage": "en-US"
      }
    },
    {
      "kind": "youtube#video",
      "etag": "AViXXtrkJavLZHwH2-OGrFP9qy8",
      "id": "4QIZE708gJ4",
      "snippet": {
        "publishedAt": "2024-05-10T14:00:06Z",
        "channelId": "UCOhtMAg7xh8wv_wUHMgFc-Q",
        "title": "Post Malone - I Had Some Help (feat. Morgan Wallen) (Official Video)",
        "description": "Official music video for “I Had Some Help” by Post Malone featuring Morgan Wallen. Get the song here: https://posty.lnk.to/ihadsomehelpYD\n \n►Subscribe for more: https://postmalone.lnk.to/subscribeYD\n \n►Shop exclusive merch: https://postmalone.lnk.to/shop\n \n►Follow Post Malone online:\nhttps://www.postmalone.com\nhttps://instagram.com/postmalone\nhttps://twitter.com/postmalone\nhttps://facebook.com/postmalone\nhttps://snapchat.com/add/postmalone\nhttps://tiktok.com/@postmalone\nhttps://discord.gg/post-malone\n \n►Lyrics:\n \n(Verse 1)\nYou got alot of nerve don’t you baby\nI only hit the curb cuz you made me\nYou’re tellin’ all your friends that I’m crazy\nLike I’m the only one\n \n(Pre Chorus)\nWhy’d you throw them stones if you\nHad a wild hair of your own or two\nLivin’ in your big glass house with a view\nI thought you knew\n \n(Chorus)\nI had some help\nIt ain’t like I can make this kind of mess all by myself\nDon’t act like you ain’t help me pull that bottle on the shelf\nBeen deep in every weekend if you couldn’t tell\nThey say team work makes the dream work\nHell I had some help\n \n(Verse 2)\nYou thought I’d take the blame for us a-crumblin’\nGo round like you ain’t guilty of somethin’\nAlready lost the game that you been runnin’\nGuess it’s catchin’ up to you, huh\nYou think that you’re so innocent\nAfter all the shit you did\nI ain’t an angel you ain’t heaven sent\nCan’t wash our hands of this\n \n(Chorus)\nI had some help\nIt ain’t like I can make this kind of mess all by myself\nDon’t act like you ain’t help me pull that bottle on the shelf\nBeen deep in every weekend if you couldn’t tell\nThey say team work makes the dream work\nHell I had some help\n \n(Bridge) (Morgan)\nIt takes two to break a heart in two, ooh\n(Bridge) (Post)\nYou blame me and baby I blame you\n(Bridge) (Morgan)\nOh if that ain’t truth\n \n(Chorus)\nI had some help\nIt ain’t like I can make this kind of mess all by myself\nDon’t act like you ain’t help me pull that bottle on the shelf\nBeen deep in every weekend if you couldn’t tell\nThey say team work makes the dream work\nHell I had some help\n \nDirector: Chris Villa\nCreative Direction: Chris Villa, Justin Clough\nExecutive Producer: Harrison Corwin\nProducer: Dylan Underhill\nLine Producer: Louis Moreschi\nDP: John Matysiak\nEditor: Chris Villa\nColorist: Walter Volpatto\nSound Design: Thomas Joren Nielsen\nVFX: Biohazard Vex\nVFX: Fifty Ruck, Rick Lancaster, Justin Hwang\nVFX Supervisor: Nicholai Vogel\nCompositing: Daniel Pianezza, Nuke Fx\n3D: Miguel Fernandes, Nicholai Vogel\nAdditional VFX: Mihajlo Stefanović, S9intvfx \nGraphic Design: Amari Kyss\nRotoscopy: Anurag Raj\nTitle Design: Sam Sblngr\nProduction Company: SHOTCLOCK\n \n#postmalone #morganwallen #ihadsomehelp\n\n\n\nMusic video by Post Malone performing I Had Some Help. © 2024 Mercury Records / Republic Records, a division of UMG Recordings, Inc.",
        "thumbnails": {
          "default": {
            "url": "https://i.ytimg.com/vi/4QIZE708gJ4/default.jpg",
            "width": 120,
            "height": 90
          },
          "medium": {
            "url": "https://i.ytimg.com/vi/4QIZE708gJ4/mqdefault.jpg",
            "width": 320,
            "height": 180
          },
          "high": {
            "url": "https://i.ytimg.com/vi/4QIZE708gJ4/hqdefault.jpg",
            "width": 480,
            "height": 360
          },
          "standard": {
            "url": "https://i.ytimg.com/vi/4QIZE708gJ4/sddefault.jpg",
            "width": 640,
            "height": 480
          },
          "maxres": {
            "url": "https://i.ytimg.com/vi/4QIZE708gJ4/maxresdefault.jpg",
            "width": 1280,
            "height": 720
          }
        },
        "channelTitle": "PostMaloneVEVO",
        "tags": [
          "post malone",
          "had some help",
          "morgan wallen",
          "post malone morgan wallen",
          "post malone had some help",
          "morgan wallen had some help",
          "had some help post malone morgan wallen",
          "posty had some help",
          "posty"
        ],
        "categoryId": "10",
        "liveBroadcastContent": "none",
        "localized": {
          "title": "Post Malone - I Had Some Help (feat. Morgan Wallen) (Official Video)",
          "description": "Official music video for “I Had Some Help” by Post Malone featuring Morgan Wallen. Get the song here: https://posty.lnk.to/ihadsomehelpYD\n \n►Subscribe for more: https://postmalone.lnk.to/subscribeYD\n \n►Shop exclusive merch: https://postmalone.lnk.to/shop\n \n►Follow Post Malone online:\nhttps://www.postmalone.com\nhttps://instagram.com/postmalone\nhttps://twitter.com/postmalone\nhttps://facebook.com/postmalone\nhttps://snapchat.com/add/postmalone\nhttps://tiktok.com/@postmalone\nhttps://discord.gg/post-malone\n \n►Lyrics:\n \n(Verse 1)\nYou got alot of nerve don’t you baby\nI only hit the curb cuz you made me\nYou’re tellin’ all your friends that I’m crazy\nLike I’m the only one\n \n(Pre Chorus)\nWhy’d you throw them stones if you\nHad a wild hair of your own or two\nLivin’ in your big glass house with a view\nI thought you knew\n \n(Chorus)\nI had some help\nIt ain’t like I can make this kind of mess all by myself\nDon’t act like you ain’t help me pull that bottle on the shelf\nBeen deep in every weekend if you couldn’t tell\nThey say team work makes the dream work\nHell I had some help\n \n(Verse 2)\nYou thought I’d take the blame for us a-crumblin’\nGo round like you ain’t guilty of somethin’\nAlready lost the game that you been runnin’\nGuess it’s catchin’ up to you, huh\nYou think that you’re so innocent\nAfter all the shit you did\nI ain’t an angel you ain’t heaven sent\nCan’t wash our hands of this\n \n(Chorus)\nI had some help\nIt ain’t like I can make this kind of mess all by myself\nDon’t act like you ain’t help me pull that bottle on the shelf\nBeen deep in every weekend if you couldn’t tell\nThey say team work makes the dream work\nHell I had some help\n \n(Bridge) (Morgan)\nIt takes two to break a heart in two, ooh\n(Bridge) (Post)\nYou blame me and baby I blame you\n(Bridge) (Morgan)\nOh if that ain’t truth\n \n(Chorus)\nI had some help\nIt ain’t like I can make this kind of mess all by myself\nDon’t act like you ain’t help me pull that bottle on the shelf\nBeen deep in every weekend if you couldn’t tell\nThey say team work makes the dream work\nHell I had some help\n \nDirector: Chris Villa\nCreative Direction: Chris Villa, Justin Clough\nExecutive Producer: Harrison Corwin\nProducer: Dylan Underhill\nLine Producer: Louis Moreschi\nDP: John Matysiak\nEditor: Chris Villa\nColorist: Walter Volpatto\nSound Design: Thomas Joren Nielsen\nVFX: Biohazard Vex\nVFX: Fifty Ruck, Rick Lancaster, Justin Hwang\nVFX Supervisor: Nicholai Vogel\nCompositing: Daniel Pianezza, Nuke Fx\n3D: Miguel Fernandes, Nicholai Vogel\nAdditional VFX: Mihajlo Stefanović, S9intvfx \nGraphic Design: Amari Kyss\nRotoscopy: Anurag Raj\nTitle Design: Sam Sblngr\nProduction Company: SHOTCLOCK\n \n#postmalone #morganwallen #ihadsomehelp\n\n\n\nMusic video by Post Malone performing I Had Some Help. © 2024 Mercury Records / Republic Records, a division of UMG Recordings, Inc."
        }
      }
    },
    {
      "kind": "youtube#video",
      "etag": "qY-jO0CPHU0nEUufJkoP48lQPy4",
      "id": "SToocHIhCN4",
      "snippet": {
        "publishedAt": "2024-05-12T08:08:40Z",
        "channelId": "UC56D-IHcUvLVFTX_8NpQMXg",
        "title": "Me VS World's Most EVIL Teacher!!",
        "description": "I spent 24 hours with the world's strictest teacher! \n\nFollow the Gang!! \nAmp World - \u200b   @AmpWorld.     @AmpWorldReacts      \nBen Azelart -     @BenAzelart            \nLexi Rivera -    @AlexaRivera      \nDrew-    @DrewBeilfuss        \nJeremy Hutchins:    @JeremyHutchins        \nAndrew Davila -    @andrewdavila6696      \nLiv:     @livswearingen        \nDom Brack -    @dominicbrack           \nPierson:     @pierson           \n\nhang out with me on social media:\nSnapChat, Add me: TheBrentRivera\nInstagram: @BrentRivera\nTwitter: @BrentRivera\nFacebook: @BrentRivera\nTikTok:  @brentrivera",
        "thumbnails": {
          "default": {
            "url": "https://i.ytimg.com/vi/SToocHIhCN4/default.jpg",
            "width": 120,
            "height": 90
          },
          "medium": {
            "url": "https://i.ytimg.com/vi/SToocHIhCN4/mqdefault.jpg",
            "width": 320,
            "height": 180
          },
          "high": {
            "url": "https://i.ytimg.com/vi/SToocHIhCN4/hqdefault.jpg",
            "width": 480,
            "height": 360
          },
          "standard": {
            "url": "https://i.ytimg.com/vi/SToocHIhCN4/sddefault.jpg",
            "width": 640,
            "height": 480
          },
          "maxres": {
            "url": "https://i.ytimg.com/vi/SToocHIhCN4/maxresdefault.jpg",
            "width": 1280,
            "height": 720
          }
        },
        "channelTitle": "Brent Rivera",
        "categoryId": "24",
        "liveBroadcastContent": "none",
        "localized": {
          "title": "Me VS World's Most EVIL Teacher!!",
          "description": "I spent 24 hours with the world's strictest teacher! \n\nFollow the Gang!! \nAmp World - \u200b   @AmpWorld.     @AmpWorldReacts      \nBen Azelart -     @BenAzelart            \nLexi Rivera -    @AlexaRivera      \nDrew-    @DrewBeilfuss        \nJeremy Hutchins:    @JeremyHutchins        \nAndrew Davila -    @andrewdavila6696      \nLiv:     @livswearingen        \nDom Brack -    @dominicbrack           \nPierson:     @pierson           \n\nhang out with me on social media:\nSnapChat, Add me: TheBrentRivera\nInstagram: @BrentRivera\nTwitter: @BrentRivera\nFacebook: @BrentRivera\nTikTok:  @brentrivera"
        },
        "defaultAudioLanguage": "en"
      }
    },
    {
      "kind": "youtube#video",
      "etag": "rBRff42JaXWVPtM8XsYZhQRNu9w",
      "id": "8gIzMPofwyM",
      "snippet": {
        "publishedAt": "2024-05-12T10:24:59Z",
        "channelId": "UCvqRdlKsE5Q8mf8YXbdIJLw",
        "title": "T1 vs BLG | DAY 11 | MSI 2024",
        "description": "MSI 2024, LIVE FROM CHENGDU PERFORMING ARTS CENTER, IN CHENGDU. #MSI2024\n\nPLAY-INS STAGE: 5/1-5/5\nBRACKET STAGE: 5/7-5/19\n\nWatch all MSI matches here!\nFULL VOD PLAYLIST - https://lolesports.com/vods/msi/msi_2024...\n\nYou can always learn more and view the full match schedule at http://www.lolesports.com.\n\nJoin the conversation on Twitter, Follow us @lolesports:\nhttps://twitter.com/lolesports\n\nLike us on FACEBOOK for important updates:\nhttp://www.facebook.com/lolesports\n\nCheck out our photos on FLICKR:\nhttp://bit.ly/lolesportsFlickr",
        "thumbnails": {
          "default": {
            "url": "https://i.ytimg.com/vi/8gIzMPofwyM/default.jpg",
            "width": 120,
            "height": 90
          },
          "medium": {
            "url": "https://i.ytimg.com/vi/8gIzMPofwyM/mqdefault.jpg",
            "width": 320,
            "height": 180
          },
          "high": {
            "url": "https://i.ytimg.com/vi/8gIzMPofwyM/hqdefault.jpg",
            "width": 480,
            "height": 360
          },
          "standard": {
            "url": "https://i.ytimg.com/vi/8gIzMPofwyM/sddefault.jpg",
            "width": 640,
            "height": 480
          },
          "maxres": {
            "url": "https://i.ytimg.com/vi/8gIzMPofwyM/maxresdefault.jpg",
            "width": 1280,
            "height": 720
          }
        },
        "channelTitle": "LoL Esports",
        "tags": [
          "lol esports",
          "league of legends",
          "lol esports live",
          "lol esports highlights",
          "lol esports worlds",
          "lol esports lcs",
          "lol esports 2021",
          "lol esports lpl",
          "lol esports vods",
          "lol esports all star",
          "lol esports academy",
          "lol esports animation",
          "lol esports best moments",
          "lol esports breakdown",
          "lol esports best plays",
          "lol esports best games",
          "lol esports best outplays",
          "lol esports channel",
          "league of legends worlds",
          "league of legends guide",
          "league of legends champions"
        ],
        "categoryId": "20",
        "liveBroadcastContent": "none",
        "defaultLanguage": "en",
        "localized": {
          "title": "T1 vs BLG | DAY 11 | MSI 2024",
          "description": "MSI 2024, LIVE FROM CHENGDU PERFORMING ARTS CENTER, IN CHENGDU. #MSI2024\n\nPLAY-INS STAGE: 5/1-5/5\nBRACKET STAGE: 5/7-5/19\n\nWatch all MSI matches here!\nFULL VOD PLAYLIST - https://lolesports.com/vods/msi/msi_2024...\n\nYou can always learn more and view the full match schedule at http://www.lolesports.com.\n\nJoin the conversation on Twitter, Follow us @lolesports:\nhttps://twitter.com/lolesports\n\nLike us on FACEBOOK for important updates:\nhttp://www.facebook.com/lolesports\n\nCheck out our photos on FLICKR:\nhttp://bit.ly/lolesportsFlickr"
        },
        "defaultAudioLanguage": "en"
      }
    },
    {
      "kind": "youtube#video",
      "etag": "P2NZXxdoShPgsS33XOd09Ap2eKE",
      "id": "_JWGVXtbRPk",
      "snippet": {
        "publishedAt": "2024-05-12T11:22:52Z",
        "channelId": "UCBB0oz7Yo_35gnbPYGKGJTA",
        "title": "Cleaning up an Abandon Barn! (Rotting for 10+ years)",
        "description": "Check Out the Merch Store! https://DieselCreek.com/ \n\nNeed a big parts washer for your shop? Check out https://www.washparts.com \n\nLike something you see in a video? good chance its linked in my Amazon Store: https://www.amazon.com/shop/dieselcreek\n\nFollow me on Instagram & Facebook @dieselcreek #DieselCreek\n\nCustom Music made for me by Vinnie Longhi of the Semi-Supervillains \nCheck them out here:  http://www.youtube.com/tssvillains\n\nCheck out these awesome recovery ropes from Yankum Ropes.\nhttps://yankum.com/?afmc=dieselcreek\nUse the code dieselcreek at checkout for 10% off your purchase! \n\nWanna send me something? Sent it to:\nDiesel Creek \nP.O. Box 109 \nBurgettstown PA 15021-010",
        "thumbnails": {
          "default": {
            "url": "https://i.ytimg.com/vi/_JWGVXtbRPk/default.jpg",
            "width": 120,
            "height": 90
          },
          "medium": {
            "url": "https://i.ytimg.com/vi/_JWGVXtbRPk/mqdefault.jpg",
            "width": 320,
            "height": 180
          },
          "high": {
            "url": "https://i.ytimg.com/vi/_JWGVXtbRPk/hqdefault.jpg",
            "width": 480,
            "height": 360
          },
          "standard": {
            "url": "https://i.ytimg.com/vi/_JWGVXtbRPk/sddefault.jpg",
            "width": 640,
            "height": 480
          },
          "maxres": {
            "url": "https://i.ytimg.com/vi/_JWGVXtbRPk/maxresdefault.jpg",
            "width": 1280,
            "height": 720
          }
        },
        "channelTitle": "Diesel Creek",
        "tags": [
          "Barn",
          "Farm",
          "heavy equipment",
          "construction",
          "digger",
          "diesel",
          "Cummins",
          "homestead",
          "building",
          "caterpillar",
          "cat",
          "Volvo",
          "JCB",
          "case",
          "excavator",
          "loader",
          "outdoors",
          "nature",
          "freedom",
          "green",
          "Enviromental",
          "hippie",
          "old soul",
          "farm",
          "woods",
          "forest",
          "Farming",
          "Komatsu",
          "cows",
          "livestock",
          "USA",
          "America"
        ],
        "categoryId": "2",
        "liveBroadcastContent": "none",
        "localized": {
          "title": "Cleaning up an Abandon Barn! (Rotting for 10+ years)",
          "description": "Check Out the Merch Store! https://DieselCreek.com/ \n\nNeed a big parts washer for your shop? Check out https://www.washparts.com \n\nLike something you see in a video? good chance its linked in my Amazon Store: https://www.amazon.com/shop/dieselcreek\n\nFollow me on Instagram & Facebook @dieselcreek #DieselCreek\n\nCustom Music made for me by Vinnie Longhi of the Semi-Supervillains \nCheck them out here:  http://www.youtube.com/tssvillains\n\nCheck out these awesome recovery ropes from Yankum Ropes.\nhttps://yankum.com/?afmc=dieselcreek\nUse the code dieselcreek at checkout for 10% off your purchase! \n\nWanna send me something? Sent it to:\nDiesel Creek \nP.O. Box 109 \nBurgettstown PA 15021-010"
        }
      }
    },
    {
      "kind": "youtube#video",
      "etag": "Nk_U3ZTAhj8RW-FaQs8AHuRf9hk",
      "id": "dvCweOmHlkk",
      "snippet": {
        "publishedAt": "2024-05-11T17:31:03Z",
        "channelId": "UC477Kvszl9JivqOxN1dFgPQ",
        "title": "I played 1 Souls-Like game you've never heard of",
        "description": "Thank you V Rising for sponsoring! Check out the game here:\nhttps://store.steampowered.com/app/1604030/V_Rising/?utm_source=IronPineapple\nWishlist on PlayStation: https://playstation.com/games/v-rising/\n\nbonus episode of Steam Dumpster Diving with somehow, once again, even more \"souls-likes\" you (probably) haven't heard of\n\ntwitter: https://twitter.com/IronPineapple_\ntwitch: https://www.twitch.tv/iron_pineapple\n\nBig thanks to:\ncobcris for animating the intro: https://twitter.com/cobcris\nVaati for co-oping with me:@VaatiVidya \nOnua for creating the SFM pose of the knight in the thumbnail: https://twitter.com/Odynom\n\nTIMESTAMPS\n0:00 intro\n2:44 The Last Oricru\n1:58:23 Outro\n\ngames played (in order of appearance)\nhttps://store.steampowered.com/app/1663640/The_Last_Oricru__Final_Cut/",
        "thumbnails": {
          "default": {
            "url": "https://i.ytimg.com/vi/dvCweOmHlkk/default.jpg",
            "width": 120,
            "height": 90
          },
          "medium": {
            "url": "https://i.ytimg.com/vi/dvCweOmHlkk/mqdefault.jpg",
            "width": 320,
            "height": 180
          },
          "high": {
            "url": "https://i.ytimg.com/vi/dvCweOmHlkk/hqdefault.jpg",
            "width": 480,
            "height": 360
          },
          "standard": {
            "url": "https://i.ytimg.com/vi/dvCweOmHlkk/sddefault.jpg",
            "width": 640,
            "height": 480
          },
          "maxres": {
            "url": "https://i.ytimg.com/vi/dvCweOmHlkk/maxresdefault.jpg",
            "width": 1280,
            "height": 720
          }
        },
        "channelTitle": "Iron Pineapple",
        "tags": [
          "soulslike",
          "souls like",
          "iron pineapple",
          "dark souls",
          "elden ring",
          "gameplay",
          "funny",
          "co-op",
          "review",
          "guide",
          "commentary"
        ],
        "categoryId": "20",
        "liveBroadcastContent": "none",
        "localized": {
          "title": "I played 1 Souls-Like game you've never heard of",
          "description": "Thank you V Rising for sponsoring! Check out the game here:\nhttps://store.steampowered.com/app/1604030/V_Rising/?utm_source=IronPineapple\nWishlist on PlayStation: https://playstation.com/games/v-rising/\n\nbonus episode of Steam Dumpster Diving with somehow, once again, even more \"souls-likes\" you (probably) haven't heard of\n\ntwitter: https://twitter.com/IronPineapple_\ntwitch: https://www.twitch.tv/iron_pineapple\n\nBig thanks to:\ncobcris for animating the intro: https://twitter.com/cobcris\nVaati for co-oping with me:@VaatiVidya \nOnua for creating the SFM pose of the knight in the thumbnail: https://twitter.com/Odynom\n\nTIMESTAMPS\n0:00 intro\n2:44 The Last Oricru\n1:58:23 Outro\n\ngames played (in order of appearance)\nhttps://store.steampowered.com/app/1663640/The_Last_Oricru__Final_Cut/"
        },
        "defaultAudioLanguage": "en"
      }
    },
    {
      "kind": "youtube#video",
      "etag": "akN9Xw3hOaVGj9w_nhEiQv_a3uo",
      "id": "TKQY2ZlIEjY",
      "snippet": {
        "publishedAt": "2024-05-10T04:00:19Z",
        "channelId": "UCKrdjiuS66yXOdEZ_cOD_TA",
        "title": "Megan Thee Stallion - BOA [Official Video]",
        "description": "The official video for Megan Thee Stallion's \"BOA\" - OUT NOW!\n\nStream \"BOA\": https://mts.lnk.to/boa\n\nGet your Hot Girl Summer tickets at\nhttps://www.MeganTheeStallion.com/\n\nText Megan Thee Stallion:\n(832) 210-1202\n\nFollow Megan Thee Stallion:\nhttps://www.instagram.com/theestallion\nhttps://twitter.com/theestallion\nhttps://www.facebook.com/theestallionn\nhttps://soundcloud.com/megan-thee-stallion\n\nLYRICS: \nI be showing my ass they mad huh\nBitches is bitter they thought it was sweet\nAll of the sudden they vegan, they don’t want beef\nTalking out veneers, I’m knockin out teeth\nI pop shit, they went pop\nThey bought birkins, I bought stock\nThey still on the boat, I’m on a yacht\nThey takin shots, I’m takin spots\nI see the shade, then they get blocked\nThey see the chain, then they went blind, yeah\nI know I’m different, I’m one of a kind, I took off on bitches and left’em behind\nHow do you hate me if I’m on yo mind\nSending me messages, ain’t valentines\nBitches is messy, but I’m petty,\nDon’t gotta edit, check the Getty\nI keep it real I keep it sexy calling for backup before they address me\nHoes do all of that typing, but never once did I get pressed\nIts obvious bitches obsessed\nIf it’s fuck me then we having sex\nIf I pop back then they go\n\nBitch yo time up\nThese bitches only hot on\nBitches doing all that womp womp womp womp womp womp\nBitch yo time up\nWhy is you not clocking out?\nDoing shit for Tik Tok\nBitch I’m really hip hop\nThey all know my shit hot\nAin’t listen when yo shit drop\nAll my diamonds dancing I ain’t need to make no Tik Tok\nBitch yo time up\n\nHair long, money long, counting up for hours\nI don’t want no minute man, fuck me for some hours\nChains wet, I’m in love with money showers\nDo do do, I love the sound of money counters, ah\nBoy I’m a player, not a savior\nNiggas and purses i got every flavor\nTake a picture I pose for the haters, showing my ass like adult entertainers\nFrom the back he can tell I’m from Texas\nYellow diamonds in my necklace\nJust crossed another opp off the checklist\nSpanking these rap bitches yeah that’s my fetish\nHe do what I tell’em, I do what I wanna do\nAll that fuckin talking but let’s see who really make a move\nPost a picture bitches call me mother now who sonning who ?\n\nBitch yo time up\nThese bitches only hot on\nBitches doing all that womp womp womp womp womp womp\nBitch yo time up\nWhy is you not clocking out?\nDoing shit for Tik Tok\nBitch I’m really hip hop\nThey all know my shit hot\nAin’t listen when yo shit drop\nAll my diamonds dancing I ain’t need to make no Tik Tok\nBitch yo time up\n\n--\n#MeganTheeStallion #BOA #OfficialVideo",
        "thumbnails": {
          "default": {
            "url": "https://i.ytimg.com/vi/TKQY2ZlIEjY/default.jpg",
            "width": 120,
            "height": 90
          },
          "medium": {
            "url": "https://i.ytimg.com/vi/TKQY2ZlIEjY/mqdefault.jpg",
            "width": 320,
            "height": 180
          },
          "high": {
            "url": "https://i.ytimg.com/vi/TKQY2ZlIEjY/hqdefault.jpg",
            "width": 480,
            "height": 360
          },
          "standard": {
            "url": "https://i.ytimg.com/vi/TKQY2ZlIEjY/sddefault.jpg",
            "width": 640,
            "height": 480
          },
          "maxres": {
            "url": "https://i.ytimg.com/vi/TKQY2ZlIEjY/maxresdefault.jpg",
            "width": 1280,
            "height": 720
          }
        },
        "channelTitle": "Megan Thee Stallion",
        "tags": [
          "Megan Thee Stallion",
          "Rap",
          "Houston",
          "Hottie",
          "Hip Hop 2019",
          "Hip Hop",
          "Megan Thee Stallion BOA",
          "BOA Megan Thee Stallion",
          "megan thee stallion BOA",
          "megan thee stallion",
          "megan thee stallion boa",
          "boa megan thee stallion",
          "boa meg thee stallion",
          "meg thee stallion boa",
          "boa",
          "BOA",
          "boa megan thee stallion new music",
          "megan thee stallion new music",
          "megan thee stallion new release",
          "boa meg",
          "Megan Thee Stallion - BOA [Official Video]",
          "boa official video",
          "megan thee stallion official video",
          "boa video"
        ],
        "categoryId": "10",
        "liveBroadcastContent": "none",
        "localized": {
          "title": "Megan Thee Stallion - BOA [Official Video]",
          "description": "The official video for Megan Thee Stallion's \"BOA\" - OUT NOW!\n\nStream \"BOA\": https://mts.lnk.to/boa\n\nGet your Hot Girl Summer tickets at\nhttps://www.MeganTheeStallion.com/\n\nText Megan Thee Stallion:\n(832) 210-1202\n\nFollow Megan Thee Stallion:\nhttps://www.instagram.com/theestallion\nhttps://twitter.com/theestallion\nhttps://www.facebook.com/theestallionn\nhttps://soundcloud.com/megan-thee-stallion\n\nLYRICS: \nI be showing my ass they mad huh\nBitches is bitter they thought it was sweet\nAll of the sudden they vegan, they don’t want beef\nTalking out veneers, I’m knockin out teeth\nI pop shit, they went pop\nThey bought birkins, I bought stock\nThey still on the boat, I’m on a yacht\nThey takin shots, I’m takin spots\nI see the shade, then they get blocked\nThey see the chain, then they went blind, yeah\nI know I’m different, I’m one of a kind, I took off on bitches and left’em behind\nHow do you hate me if I’m on yo mind\nSending me messages, ain’t valentines\nBitches is messy, but I’m petty,\nDon’t gotta edit, check the Getty\nI keep it real I keep it sexy calling for backup before they address me\nHoes do all of that typing, but never once did I get pressed\nIts obvious bitches obsessed\nIf it’s fuck me then we having sex\nIf I pop back then they go\n\nBitch yo time up\nThese bitches only hot on\nBitches doing all that womp womp womp womp womp womp\nBitch yo time up\nWhy is you not clocking out?\nDoing shit for Tik Tok\nBitch I’m really hip hop\nThey all know my shit hot\nAin’t listen when yo shit drop\nAll my diamonds dancing I ain’t need to make no Tik Tok\nBitch yo time up\n\nHair long, money long, counting up for hours\nI don’t want no minute man, fuck me for some hours\nChains wet, I’m in love with money showers\nDo do do, I love the sound of money counters, ah\nBoy I’m a player, not a savior\nNiggas and purses i got every flavor\nTake a picture I pose for the haters, showing my ass like adult entertainers\nFrom the back he can tell I’m from Texas\nYellow diamonds in my necklace\nJust crossed another opp off the checklist\nSpanking these rap bitches yeah that’s my fetish\nHe do what I tell’em, I do what I wanna do\nAll that fuckin talking but let’s see who really make a move\nPost a picture bitches call me mother now who sonning who ?\n\nBitch yo time up\nThese bitches only hot on\nBitches doing all that womp womp womp womp womp womp\nBitch yo time up\nWhy is you not clocking out?\nDoing shit for Tik Tok\nBitch I’m really hip hop\nThey all know my shit hot\nAin’t listen when yo shit drop\nAll my diamonds dancing I ain’t need to make no Tik Tok\nBitch yo time up\n\n--\n#MeganTheeStallion #BOA #OfficialVideo"
        },
        "defaultAudioLanguage": "en"
      }
    },
    {
      "kind": "youtube#video",
      "etag": "-OxszKdmnufckM4iot2GYXAlTAs",
      "id": "2KC-8IULfqY",
      "snippet": {
        "publishedAt": "2024-05-10T16:00:06Z",
        "channelId": "UCCdbL-yl7Qa_vurbYWdn5SA",
        "title": "Ice Spice - Gimmie A Light (Official Video)",
        "description": "Stream & Download Ice Spice \"Gimmie A Light\" new single here: \nhttps://IceSpice.lnk.to/GimmieALight\n\nShop Ice Spice Merch: \nhttps://IceSpice.lnk.to/Shop\n\nFollow Ice Spice Everywhere:\nFacebook:  https://www.facebook.com/icespicemusic1/\nTwitter:  https://twitter.com/icespicee_\nInstagram: https://www.instagram.com/icespice/ \nTikTok: https://www.tiktok.com/icespicee\n\nMusic video by Ice Spice performing Gimmie A Light. © 2024 Dolo Entertainment, Inc., under exclusive license to UMG Recordings, Inc. & 10K Projects, LLC.\n\nhttp://vevo.ly/WLyrWa",
        "thumbnails": {
          "default": {
            "url": "https://i.ytimg.com/vi/2KC-8IULfqY/default.jpg",
            "width": 120,
            "height": 90
          },
          "medium": {
            "url": "https://i.ytimg.com/vi/2KC-8IULfqY/mqdefault.jpg",
            "width": 320,
            "height": 180
          },
          "high": {
            "url": "https://i.ytimg.com/vi/2KC-8IULfqY/hqdefault.jpg",
            "width": 480,
            "height": 360
          },
          "standard": {
            "url": "https://i.ytimg.com/vi/2KC-8IULfqY/sddefault.jpg",
            "width": 640,
            "height": 480
          },
          "maxres": {
            "url": "https://i.ytimg.com/vi/2KC-8IULfqY/maxresdefault.jpg",
            "width": 1280,
            "height": 720
          }
        },
        "channelTitle": "IceSpiceVEVO",
        "tags": [
          "Ice",
          "Spice",
          "Gimmie",
          "Light",
          "10K",
          "Projects/Capitol",
          "Records",
          "Hip",
          "Hop"
        ],
        "categoryId": "10",
        "liveBroadcastContent": "none",
        "localized": {
          "title": "Ice Spice - Gimmie A Light (Official Video)",
          "description": "Stream & Download Ice Spice \"Gimmie A Light\" new single here: \nhttps://IceSpice.lnk.to/GimmieALight\n\nShop Ice Spice Merch: \nhttps://IceSpice.lnk.to/Shop\n\nFollow Ice Spice Everywhere:\nFacebook:  https://www.facebook.com/icespicemusic1/\nTwitter:  https://twitter.com/icespicee_\nInstagram: https://www.instagram.com/icespice/ \nTikTok: https://www.tiktok.com/icespicee\n\nMusic video by Ice Spice performing Gimmie A Light. © 2024 Dolo Entertainment, Inc., under exclusive license to UMG Recordings, Inc. & 10K Projects, LLC.\n\nhttp://vevo.ly/WLyrWa"
        }
      }
    },
    {
      "kind": "youtube#video",
      "etag": "0u4hsY9PNfkhXq_eeg7NX7WXnqM",
      "id": "0WEP6oy25lY",
      "snippet": {
        "publishedAt": "2024-05-12T06:20:14Z",
        "channelId": "UCbzRzJNHx7ZLlJML9BjZQVQ",
        "title": "Vasiliy Lomachenko And George Kambosos Share Their Thoughts Post-Fight",
        "description": "Listen to #vasiliylomachenko and #georgekambososjr share their thoughts immediately after their fight at a sold-out arena in Perth, Australia. #highlights \n\nSubscribe to our YouTube channel to get notified about the latest highlights, free full fights, and fight week content as it's posted.\n\nFollow Top Rank on X: http://www.twitter.com/trboxing\nFollow Top Rank on Instagram: http://www.instagram.com/toprank\nFollow Top Rank on TikTok: https://www.tiktok.com/@trboxing\nLike Top Rank on Facebook: http://www.facebook.com/trboxing",
        "thumbnails": {
          "default": {
            "url": "https://i.ytimg.com/vi/0WEP6oy25lY/default.jpg",
            "width": 120,
            "height": 90
          },
          "medium": {
            "url": "https://i.ytimg.com/vi/0WEP6oy25lY/mqdefault.jpg",
            "width": 320,
            "height": 180
          },
          "high": {
            "url": "https://i.ytimg.com/vi/0WEP6oy25lY/hqdefault.jpg",
            "width": 480,
            "height": 360
          },
          "standard": {
            "url": "https://i.ytimg.com/vi/0WEP6oy25lY/sddefault.jpg",
            "width": 640,
            "height": 480
          },
          "maxres": {
            "url": "https://i.ytimg.com/vi/0WEP6oy25lY/maxresdefault.jpg",
            "width": 1280,
            "height": 720
          }
        },
        "channelTitle": "Top Rank Boxing",
        "tags": [
          "top rank boxing",
          "boxing",
          "vasiliy lomachenko vs george kambosos fight highlights",
          "vasiliy lomachenko vs george kambosos stoppage",
          "vasiliy lomachenko vs george kambosos interview",
          "vasiliy lomachenko vs george kambosos fight",
          "vasiliy lomachenko fight",
          "vasiliy lomachenko devin haney",
          "vasiliy lomachenko george kambosos",
          "vasiliy lomachenko george kambosos post fight",
          "vasiliy lomachenko highlights",
          "vasiliy lomachenko and george kambosos interview",
          "vasiliy lomachenko post fight interview"
        ],
        "categoryId": "17",
        "liveBroadcastContent": "none",
        "localized": {
          "title": "Vasiliy Lomachenko And George Kambosos Share Their Thoughts Post-Fight",
          "description": "Listen to #vasiliylomachenko and #georgekambososjr share their thoughts immediately after their fight at a sold-out arena in Perth, Australia. #highlights \n\nSubscribe to our YouTube channel to get notified about the latest highlights, free full fights, and fight week content as it's posted.\n\nFollow Top Rank on X: http://www.twitter.com/trboxing\nFollow Top Rank on Instagram: http://www.instagram.com/toprank\nFollow Top Rank on TikTok: https://www.tiktok.com/@trboxing\nLike Top Rank on Facebook: http://www.facebook.com/trboxing"
        },
        "defaultAudioLanguage": "en-US"
      }
    },
    {
      "kind": "youtube#video",
      "etag": "9iIJB3rE6DU6SMjFykcSO9yFX5c",
      "id": "MTxFIFY7Fj8",
      "snippet": {
        "publishedAt": "2024-05-12T02:14:02Z",
        "channelId": "UCRpjHHu8ivVWs73uxHlWwFA",
        "title": "WINNER'S PERFORMANCE: Nemo - The Code ✨ | Switzerland 🇨🇭 | Eurovision 2024 | Watch on Peacock",
        "description": "Subscribe and 🔔 to Eurovision 👉 https://www.youtube.com/user/eurovision?sub_confirmation=1 \u200b\n\nNemo's winner reprise of 'The Code' for Switzerland after winning the Grand Final of the Eurovision Song Contest 2024 at Malmö, Sweden.\n\nYou can watch all the performances of the Grand Final of the 68th Eurovision Song Contest on Peacock: https://www.peacocktv.com/\n\n-\u200b\nWe are #UnitedByMusic. The Eurovision Song Contest celebrates diversity through music. Please keep your comments respectful. We will not tolerate racism, sexism, ableism, homophobia, transphobia, body-shaming or any other derogatory or hostile language. Offensive users will be blocked and reported.\n\nSubscribe to the Official Eurovision Song Contest Podcast: https://pod.link/1617767675\nFollow us on TikTok: https://www.tiktok.com/@Eurovision \nFollow us on Instagram: https://www.instagram.com/eurovision \nFollow us on Threads: https://threads.net/Eurovision\nFollow us on Facebook: https://facebook.com/EurovisionSongContest\n\nIf you want to know more about the Eurovision Song Contest, visit https://eurovision.tv\n\nShop for official Eurovision Song Contest merchandise: https://shop.eurovision.tv/",
        "thumbnails": {
          "default": {
            "url": "https://i.ytimg.com/vi/MTxFIFY7Fj8/default.jpg",
            "width": 120,
            "height": 90
          },
          "medium": {
            "url": "https://i.ytimg.com/vi/MTxFIFY7Fj8/mqdefault.jpg",
            "width": 320,
            "height": 180
          },
          "high": {
            "url": "https://i.ytimg.com/vi/MTxFIFY7Fj8/hqdefault.jpg",
            "width": 480,
            "height": 360
          },
          "standard": {
            "url": "https://i.ytimg.com/vi/MTxFIFY7Fj8/sddefault.jpg",
            "width": 640,
            "height": 480
          },
          "maxres": {
            "url": "https://i.ytimg.com/vi/MTxFIFY7Fj8/maxresdefault.jpg",
            "width": 1280,
            "height": 720
          }
        },
        "channelTitle": "Eurovision Song Contest",
        "tags": [
          "Eurovision Song Contest",
          "Eurovision",
          "Eurovision Tickets",
          "EBU",
          "Eurovision 2024",
          "ESC2024",
          "#UnitedByMusic",
          "Malmö",
          "Malmö 2024"
        ],
        "categoryId": "24",
        "liveBroadcastContent": "none",
        "defaultLanguage": "en",
        "localized": {
          "title": "WINNER'S PERFORMANCE: Nemo - The Code ✨ | Switzerland 🇨🇭 | Eurovision 2024 | Watch on Peacock",
          "description": "Subscribe and 🔔 to Eurovision 👉 https://www.youtube.com/user/eurovision?sub_confirmation=1 \u200b\n\nNemo's winner reprise of 'The Code' for Switzerland after winning the Grand Final of the Eurovision Song Contest 2024 at Malmö, Sweden.\n\nYou can watch all the performances of the Grand Final of the 68th Eurovision Song Contest on Peacock: https://www.peacocktv.com/\n\n-\u200b\nWe are #UnitedByMusic. The Eurovision Song Contest celebrates diversity through music. Please keep your comments respectful. We will not tolerate racism, sexism, ableism, homophobia, transphobia, body-shaming or any other derogatory or hostile language. Offensive users will be blocked and reported.\n\nSubscribe to the Official Eurovision Song Contest Podcast: https://pod.link/1617767675\nFollow us on TikTok: https://www.tiktok.com/@Eurovision \nFollow us on Instagram: https://www.instagram.com/eurovision \nFollow us on Threads: https://threads.net/Eurovision\nFollow us on Facebook: https://facebook.com/EurovisionSongContest\n\nIf you want to know more about the Eurovision Song Contest, visit https://eurovision.tv\n\nShop for official Eurovision Song Contest merchandise: https://shop.eurovision.tv/"
        },
        "defaultAudioLanguage": "en"
      }
    },
    {
      "kind": "youtube#video",
      "etag": "mQzy28dktLyqY4n4_mSEV_YndbQ",
      "id": "B3x86Eull2U",
      "snippet": {
        "publishedAt": "2024-05-11T01:08:39Z",
        "channelId": "UCDR8cvjALazMm2j9hOar8_g",
        "title": "Young Sheldon 7x13 \"Funeral\" / 7x14 \"Memoir\" Promo (HD) Series Finale",
        "description": "Young Sheldon 7x13 \"Funeral\" & 7x14 \"Memoir\"  Promo (Series Finale) - YOUNG SHELDON ends its seven-year run with a must-see two-episode series finale. Jim Parsons and Mayim Bialik reprise their roles as Sheldon Cooper and Amy Farrah Fowler in an unforgettable hour of television, on the series finale of YOUNG SHELDON, Thursday, May 16th on CBS. Subscribe to tvpromosdb on Youtube for more Young Sheldon season 7 promos in HD!\n\nYoung Sheldon official website: https://www.cbs.com/shows/young-sheldon/\nWatch more Young Sheldon Season 7 videos: https://www.youtube.com/playlist?list=PLfrisy2KXzkc1FZtZg6zj94Gm_Gqa9yTo\nLike Young Sheldon on Facebook: https://www.facebook.com/YoungSheldonCBS\nFollow Young Sheldon on Twitter: https://twitter.com/YoungSheldon\nFollow Young Sheldon on Instagram: https://www.instagram.com/YoungSheldonCBS\n\nYoung Sheldon 7x13 \"Funeral\" & 7x14 \"Memoir\" Promo/Preview (Series Finale)\nYoung Sheldon Season 7 Episode 13 & 14 Promo\nYoung Sheldon Season 7 Series Finale Promo\nYoung Sheldon S07E13 & S07E14 Promo  (Series Finale)\n\n#YoungSheldon\n\n» Watch Young Sheldon Thursdays at 8:00pm on CBS\n» Starring: Iain Armitage, Zoe Perry, Lance Barber, Raegan Revord, Montana Jordan, Jim Parsons",
        "thumbnails": {
          "default": {
            "url": "https://i.ytimg.com/vi/B3x86Eull2U/default.jpg",
            "width": 120,
            "height": 90
          },
          "medium": {
            "url": "https://i.ytimg.com/vi/B3x86Eull2U/mqdefault.jpg",
            "width": 320,
            "height": 180
          },
          "high": {
            "url": "https://i.ytimg.com/vi/B3x86Eull2U/hqdefault.jpg",
            "width": 480,
            "height": 360
          },
          "standard": {
            "url": "https://i.ytimg.com/vi/B3x86Eull2U/sddefault.jpg",
            "width": 640,
            "height": 480
          },
          "maxres": {
            "url": "https://i.ytimg.com/vi/B3x86Eull2U/maxresdefault.jpg",
            "width": 1280,
            "height": 720
          }
        },
        "channelTitle": "TV Promos",
        "tags": [
          "young sheldon 7x13 promo",
          "young sheldon 7x13",
          "young sheldon season 7 episode 13 promo",
          "young sheldon 7x13 preview",
          "young sheldon 7x13 trailer",
          "young sheldon season 7",
          "young sheldon s07e13",
          "young sheldon (tv program)",
          "young sheldon series finale",
          "young sheldon series finale promo",
          "iain armitage",
          "zoe perry",
          "jim parsons",
          "young sheldon promo",
          "tvpromosdb",
          "young sheldon",
          "7x13",
          "promo",
          "season",
          "episode",
          "trailer",
          "funeral"
        ],
        "categoryId": "24",
        "liveBroadcastContent": "none",
        "defaultLanguage": "en-US",
        "localized": {
          "title": "Young Sheldon 7x13 \"Funeral\" / 7x14 \"Memoir\" Promo (HD) Series Finale",
          "description": "Young Sheldon 7x13 \"Funeral\" & 7x14 \"Memoir\"  Promo (Series Finale) - YOUNG SHELDON ends its seven-year run with a must-see two-episode series finale. Jim Parsons and Mayim Bialik reprise their roles as Sheldon Cooper and Amy Farrah Fowler in an unforgettable hour of television, on the series finale of YOUNG SHELDON, Thursday, May 16th on CBS. Subscribe to tvpromosdb on Youtube for more Young Sheldon season 7 promos in HD!\n\nYoung Sheldon official website: https://www.cbs.com/shows/young-sheldon/\nWatch more Young Sheldon Season 7 videos: https://www.youtube.com/playlist?list=PLfrisy2KXzkc1FZtZg6zj94Gm_Gqa9yTo\nLike Young Sheldon on Facebook: https://www.facebook.com/YoungSheldonCBS\nFollow Young Sheldon on Twitter: https://twitter.com/YoungSheldon\nFollow Young Sheldon on Instagram: https://www.instagram.com/YoungSheldonCBS\n\nYoung Sheldon 7x13 \"Funeral\" & 7x14 \"Memoir\" Promo/Preview (Series Finale)\nYoung Sheldon Season 7 Episode 13 & 14 Promo\nYoung Sheldon Season 7 Series Finale Promo\nYoung Sheldon S07E13 & S07E14 Promo  (Series Finale)\n\n#YoungSheldon\n\n» Watch Young Sheldon Thursdays at 8:00pm on CBS\n» Starring: Iain Armitage, Zoe Perry, Lance Barber, Raegan Revord, Montana Jordan, Jim Parsons"
        },
        "defaultAudioLanguage": "en-US"
      }
    },
    {
      "kind": "youtube#video",
      "etag": "k8SWwJaYbl_UQXGon4jcjaYfMgg",
      "id": "9jZ2YhKkjlk",
      "snippet": {
        "publishedAt": "2024-05-11T19:00:00Z",
        "channelId": "UCCiQtqwCnPLL9sRJMZUc_8A",
        "title": "I Tricked Brawadis into Eating the World's Spiciest Chip…",
        "description": "Hopefully you guys enjoyed this video! If you did, please SMASH that like button and don't forget to SUBSCRIBE! \n\nStay Connected-\nAll My Links - https://hoo.be/shermantheverman\nInstagram- https://www.instagram.com/shermantheverman/\nTwitter- https://twitter.com/anthonyjabs\nSnapchat- Anthonyjabrnike\nTwtich - https://www.twitch.tv/shermantheverman\n\n\nFor all Business inquiries: andrew@257media.com",
        "thumbnails": {
          "default": {
            "url": "https://i.ytimg.com/vi/9jZ2YhKkjlk/default.jpg",
            "width": 120,
            "height": 90
          },
          "medium": {
            "url": "https://i.ytimg.com/vi/9jZ2YhKkjlk/mqdefault.jpg",
            "width": 320,
            "height": 180
          },
          "high": {
            "url": "https://i.ytimg.com/vi/9jZ2YhKkjlk/hqdefault.jpg",
            "width": 480,
            "height": 360
          },
          "standard": {
            "url": "https://i.ytimg.com/vi/9jZ2YhKkjlk/sddefault.jpg",
            "width": 640,
            "height": 480
          },
          "maxres": {
            "url": "https://i.ytimg.com/vi/9jZ2YhKkjlk/maxresdefault.jpg",
            "width": 1280,
            "height": 720
          }
        },
        "channelTitle": "Sherman",
        "tags": [
          "#shermantheverman",
          "#faZerug",
          "Vlog",
          "Brawadis",
          "Anthony Jabro",
          "Haunted",
          "Scary",
          "Stories",
          "funny",
          "comedy",
          "rug",
          "sherman",
          "verman",
          "girlfriend",
          "prank",
          "challenge",
          "vlogs"
        ],
        "categoryId": "24",
        "liveBroadcastContent": "none",
        "localized": {
          "title": "I Tricked Brawadis into Eating the World's Spiciest Chip…",
          "description": "Hopefully you guys enjoyed this video! If you did, please SMASH that like button and don't forget to SUBSCRIBE! \n\nStay Connected-\nAll My Links - https://hoo.be/shermantheverman\nInstagram- https://www.instagram.com/shermantheverman/\nTwitter- https://twitter.com/anthonyjabs\nSnapchat- Anthonyjabrnike\nTwtich - https://www.twitch.tv/shermantheverman\n\n\nFor all Business inquiries: andrew@257media.com"
        }
      }
    },
    {
      "kind": "youtube#video",
      "etag": "1ALQWjiaz44EP_jCK3fD1NG_a_w",
      "id": "lRmnCjb0cmM",
      "snippet": {
        "publishedAt": "2024-05-11T18:00:33Z",
        "channelId": "UCnJutVTtn3ZXyapoGUmuRTA",
        "title": "UNEXPECTED OUTCOMES (#2) | Gielinor Games",
        "description": "Rediscover your love for fantasy by listening to Songs of Chaos: https://link.michaelrmiller.co.uk/SoupRS\n\n\n► Merch: https://www.bonfire.com/store/soup/\n► Patreon: https://www.patreon.com/souprs\n\nWelcome to the Gielinor Games. Eighteen of your favorite content creators will be competing in weekly challenges and eliminations to win a growing prize pool starting at 15 billion gp. But in the end, only one person can win! \n\nSeason 4 Player Socials: https://docs.google.com/document/d/13Yzn4krthcYA-Qp4i4Tz0dKx-ukSWSvUIU7ok52EZ7Y/edit?usp=sharing\n\n► http://www.twitter.com/SoupRS \n► http://www.twitch.tv/Soup\n\nSongs:\n(If you'd like to know any of the songs, please leave a comment below or send me a DM on Twitter @ SoupRS)\n\n► Play Oldschool Runescape (Free online MMORPG by Jagex) here: http://oldschool.runescape.com/\n\nMusic from:\nWest One Music Production\nArtlist - https://artlist.io/referral/3400330/Stefan",
        "thumbnails": {
          "default": {
            "url": "https://i.ytimg.com/vi/lRmnCjb0cmM/default.jpg",
            "width": 120,
            "height": 90
          },
          "medium": {
            "url": "https://i.ytimg.com/vi/lRmnCjb0cmM/mqdefault.jpg",
            "width": 320,
            "height": 180
          },
          "high": {
            "url": "https://i.ytimg.com/vi/lRmnCjb0cmM/hqdefault.jpg",
            "width": 480,
            "height": 360
          },
          "standard": {
            "url": "https://i.ytimg.com/vi/lRmnCjb0cmM/sddefault.jpg",
            "width": 640,
            "height": 480
          },
          "maxres": {
            "url": "https://i.ytimg.com/vi/lRmnCjb0cmM/maxresdefault.jpg",
            "width": 1280,
            "height": 720
          }
        },
        "channelTitle": "SoupRS",
        "tags": [
          "Oldschool Runescape",
          "old school runescape",
          "OSRS",
          "runescape",
          "gielinor games",
          "gielinor games season 2",
          "b0aty",
          "settled",
          "framed",
          "torvesta",
          "c engineer",
          "kempq",
          "skill specs",
          "solomission",
          "9rain",
          "gunschilli",
          "j1mmy",
          "poisonedpotion",
          "ditterbitter",
          "verf",
          "evscape",
          "flutten",
          "tanzoo",
          "virtoso",
          "zulu",
          "skiddler",
          "survivor",
          "osrs survivor",
          "osrs game show",
          "osrs challenges",
          "osrs money making",
          "gold rush",
          "osrs MILLIOns",
          "osrs billions",
          "osrs gp",
          "westham",
          "dino",
          "faux",
          "mr mammal",
          "mmorpgrs",
          "roidie",
          "zoepancakes",
          "zecookies"
        ],
        "categoryId": "20",
        "liveBroadcastContent": "none",
        "localized": {
          "title": "UNEXPECTED OUTCOMES (#2) | Gielinor Games",
          "description": "Rediscover your love for fantasy by listening to Songs of Chaos: https://link.michaelrmiller.co.uk/SoupRS\n\n\n► Merch: https://www.bonfire.com/store/soup/\n► Patreon: https://www.patreon.com/souprs\n\nWelcome to the Gielinor Games. Eighteen of your favorite content creators will be competing in weekly challenges and eliminations to win a growing prize pool starting at 15 billion gp. But in the end, only one person can win! \n\nSeason 4 Player Socials: https://docs.google.com/document/d/13Yzn4krthcYA-Qp4i4Tz0dKx-ukSWSvUIU7ok52EZ7Y/edit?usp=sharing\n\n► http://www.twitter.com/SoupRS \n► http://www.twitch.tv/Soup\n\nSongs:\n(If you'd like to know any of the songs, please leave a comment below or send me a DM on Twitter @ SoupRS)\n\n► Play Oldschool Runescape (Free online MMORPG by Jagex) here: http://oldschool.runescape.com/\n\nMusic from:\nWest One Music Production\nArtlist - https://artlist.io/referral/3400330/Stefan"
        },
        "defaultAudioLanguage": "en"
      }
    },
    {
      "kind": "youtube#video",
      "etag": "dElhxpElmcfqXUpbabZTyx4c_6o",
      "id": "mrUe7JmecNQ",
      "snippet": {
        "publishedAt": "2024-05-11T15:00:43Z",
        "channelId": "UC4ijq8Cg-8zQKx8OH12dUSw",
        "title": "We Tried Van Life in the Middle East (full tour)",
        "description": "I don't know what's better? Van life in Oman or this incredible Unimog! We spent 9 days overloading this beautiful country, enjoy part 1 of 3! Get a free bottle of immune supporting Vitamin D drops + 5 individual travel packs, both FREE with your first purchase of AG1! Click: http://drinkag1.com/karaandnate\n\nHUGE thanks to Freedom Overland for the epic Unimog build! Check them out here! - https://freedom-overland.com/ \n\nEpisode 925 | Filmed April 2024 | Oman days 1-3\n\n✈️ Daily Drop is our *FREE travel newsletter!* Get all the best travel news, tips, and tricks every weekday in your inbox by subscribing here ➡️\nhttps://faredrop.app/ytd_220827 \n\n📸 Get behind the scenes content on our Instagram! @karaandnate\nhttps://www.instagram.com/karaandnate/ \n\n🌎 We created FareDrop to help you score super cheap international flights! Try it risk free and get flight deals up to 80% off ➡️\nhttps://faredrop.app/ytd_220129 \n\n📧 Read our Sunday Summary email to know what goes on between videos -\nhttps://karaandnate.com/sunday-summary/ \n\n🎶 Here’s where we got all of our copyright free songs used in this episode -\nhttp://bit.ly/epidemic_sound\n\n——————————————————\n\nWho are Kara and Nate?! \nWatch our documentary here: https://www.youtube.com/watch?v=FuFv4iF8wgg&t=1s \n\nOriginally from Nashville, Tennessee, we got married 2013 and were super “normal.” I was a teacher and Nate started a small printing business from the spare bedroom of our apartment. \n\nWe discovered the world of “travel hacking” while planning our honeymoon & became addicted ;)\n\nSo after 2 years of obsessively saving $35k and over 2 million miles and points, we sold our cars and apartment and left home January 10, 2016 for a “one year” trip around the world.\n\nOur goal was to see as many places as possible before we ran out of money and went back home to “normal life.” We started this channel to share our experiences with friends and family, but quickly fell in love with living on the road and found a new passion for capturing our travels through video. So we did everything we could to keep going.\n\n4 years later, we achieved our new goal of visiting 100 countries and all 7 continents. We had no plans to slow down, until 2020 forced us to ;) Which is when we bought a converted van to start exploring our own country for the first time!\n\nAfter ~2 years of van life, we are back to full time international traveling! And now we are in our 9TH YEAR of finding the best adventures the world has to offer :) \n\nWe are incredibly grateful to be able to continue doing something we love every day. 😊🎥🌎 Thank you to everyone who has been a part of our journey!\n\n00:00 Oman road trip\n03:13 Full Unimog Tour\n10:54 Inside tour of the Unimog\n19:50 Putting it to the test\n25:24 our beach campsite\n27:06 Bioluminescence! \n28:07 Bloops",
        "thumbnails": {
          "default": {
            "url": "https://i.ytimg.com/vi/mrUe7JmecNQ/default.jpg",
            "width": 120,
            "height": 90
          },
          "medium": {
            "url": "https://i.ytimg.com/vi/mrUe7JmecNQ/mqdefault.jpg",
            "width": 320,
            "height": 180
          },
          "high": {
            "url": "https://i.ytimg.com/vi/mrUe7JmecNQ/hqdefault.jpg",
            "width": 480,
            "height": 360
          },
          "standard": {
            "url": "https://i.ytimg.com/vi/mrUe7JmecNQ/sddefault.jpg",
            "width": 640,
            "height": 480
          },
          "maxres": {
            "url": "https://i.ytimg.com/vi/mrUe7JmecNQ/maxresdefault.jpg",
            "width": 1280,
            "height": 720
          }
        },
        "channelTitle": "Kara and Nate",
        "tags": [
          "van life",
          "expedition vehicle",
          "expedition truck",
          "mercedes unimog",
          "rv life",
          "van tour",
          "unimog camper",
          "truck camper",
          "camper truck",
          "off road camper",
          "van life build",
          "van life tour",
          "van life vlog",
          "kara and nate",
          "oman",
          "overlanding",
          "overlanding oman",
          "overlanding unimog",
          "unimog",
          "unimog tour",
          "1985 unimog",
          "unimog conversion",
          "kara and nate van life",
          "kara and nate oman",
          "best things to do in oman",
          "where to camp in oman",
          "overlanding dubai",
          "middle east",
          "off road"
        ],
        "categoryId": "19",
        "liveBroadcastContent": "none",
        "localized": {
          "title": "We Tried Van Life in the Middle East (full tour)",
          "description": "I don't know what's better? Van life in Oman or this incredible Unimog! We spent 9 days overloading this beautiful country, enjoy part 1 of 3! Get a free bottle of immune supporting Vitamin D drops + 5 individual travel packs, both FREE with your first purchase of AG1! Click: http://drinkag1.com/karaandnate\n\nHUGE thanks to Freedom Overland for the epic Unimog build! Check them out here! - https://freedom-overland.com/ \n\nEpisode 925 | Filmed April 2024 | Oman days 1-3\n\n✈️ Daily Drop is our *FREE travel newsletter!* Get all the best travel news, tips, and tricks every weekday in your inbox by subscribing here ➡️\nhttps://faredrop.app/ytd_220827 \n\n📸 Get behind the scenes content on our Instagram! @karaandnate\nhttps://www.instagram.com/karaandnate/ \n\n🌎 We created FareDrop to help you score super cheap international flights! Try it risk free and get flight deals up to 80% off ➡️\nhttps://faredrop.app/ytd_220129 \n\n📧 Read our Sunday Summary email to know what goes on between videos -\nhttps://karaandnate.com/sunday-summary/ \n\n🎶 Here’s where we got all of our copyright free songs used in this episode -\nhttp://bit.ly/epidemic_sound\n\n——————————————————\n\nWho are Kara and Nate?! \nWatch our documentary here: https://www.youtube.com/watch?v=FuFv4iF8wgg&t=1s \n\nOriginally from Nashville, Tennessee, we got married 2013 and were super “normal.” I was a teacher and Nate started a small printing business from the spare bedroom of our apartment. \n\nWe discovered the world of “travel hacking” while planning our honeymoon & became addicted ;)\n\nSo after 2 years of obsessively saving $35k and over 2 million miles and points, we sold our cars and apartment and left home January 10, 2016 for a “one year” trip around the world.\n\nOur goal was to see as many places as possible before we ran out of money and went back home to “normal life.” We started this channel to share our experiences with friends and family, but quickly fell in love with living on the road and found a new passion for capturing our travels through video. So we did everything we could to keep going.\n\n4 years later, we achieved our new goal of visiting 100 countries and all 7 continents. We had no plans to slow down, until 2020 forced us to ;) Which is when we bought a converted van to start exploring our own country for the first time!\n\nAfter ~2 years of van life, we are back to full time international traveling! And now we are in our 9TH YEAR of finding the best adventures the world has to offer :) \n\nWe are incredibly grateful to be able to continue doing something we love every day. 😊🎥🌎 Thank you to everyone who has been a part of our journey!\n\n00:00 Oman road trip\n03:13 Full Unimog Tour\n10:54 Inside tour of the Unimog\n19:50 Putting it to the test\n25:24 our beach campsite\n27:06 Bioluminescence! \n28:07 Bloops"
        },
        "defaultAudioLanguage": "en"
      }
    },
    {
      "kind": "youtube#video",
      "etag": "nt_nIxuxsQufnnpQo_X62SGY92c",
      "id": "9ba-BC6-O1Y",
      "snippet": {
        "publishedAt": "2024-05-11T15:00:06Z",
        "channelId": "UC_1QUZJSTYqda_dVYlNV03w",
        "title": "I Built an INSANE Electric Mini Moto (+60mph!)",
        "description": "Best DIY electric pit bike supermoto ever!\n\n✅ DISCOUNT CODE \"SURRONSTER5\" ✅\nElectro&Co Website https://electroandcompany.com/\nRazor Parts https://electroandcompany.com/collections/razor-accessories\nKit https://electroandcompany.com/collections/razor-kits/products/extreme-11-000w-razor-kit?variant=48317352870186\n✅ DISCOUNT CODE \"SURRONSTER5\" ✅\n\nRazor SX500 https://amzn.to/3WuP818\nRazor MX500 https://amzn.to/3UJCIB8\n\nThrift Store 0:00\nParts and Cost 0:30\nHow to Build 2:05\nRazor vs Talaria 8:37\nPre-Ride 11:31\nTest Ride 13:03\n\nkey words: electric minibike diy electric bike how to build an electric bike how to build an electric pitbike budget electric bike tutorial cheapest electric dirt bike razor sx500 upgrade how to make razor bikes faster how to build a 72v razor how to build a razor for cheap how to make an electric bike faster how to make an electric dirtbike faster mini supermoto diy thrift store bike surronster thrift store minimoto 72v razor build tutorial electro and co razor build low cost electric dirtbike cheapest electric pit bike how to build how to build an electric stunt bike best electric bike for wheelies best electric dirtbike for wheelies",
        "thumbnails": {
          "default": {
            "url": "https://i.ytimg.com/vi/9ba-BC6-O1Y/default.jpg",
            "width": 120,
            "height": 90
          },
          "medium": {
            "url": "https://i.ytimg.com/vi/9ba-BC6-O1Y/mqdefault.jpg",
            "width": 320,
            "height": 180
          },
          "high": {
            "url": "https://i.ytimg.com/vi/9ba-BC6-O1Y/hqdefault.jpg",
            "width": 480,
            "height": 360
          },
          "standard": {
            "url": "https://i.ytimg.com/vi/9ba-BC6-O1Y/sddefault.jpg",
            "width": 640,
            "height": 480
          },
          "maxres": {
            "url": "https://i.ytimg.com/vi/9ba-BC6-O1Y/maxresdefault.jpg",
            "width": 1280,
            "height": 720
          }
        },
        "channelTitle": "Sur Ronster",
        "tags": [
          "mini",
          "bike",
          "ebike",
          "howto",
          "electric",
          "razor",
          "diy",
          "fastest",
          "cheapest",
          "cheap",
          "tutorial",
          "test",
          "supermoto",
          "best",
          "dirtbike",
          "surron",
          "talaira",
          "sx500",
          "mx500",
          "electroandco"
        ],
        "categoryId": "2",
        "liveBroadcastContent": "none",
        "localized": {
          "title": "I Built an INSANE Electric Mini Moto (+60mph!)",
          "description": "Best DIY electric pit bike supermoto ever!\n\n✅ DISCOUNT CODE \"SURRONSTER5\" ✅\nElectro&Co Website https://electroandcompany.com/\nRazor Parts https://electroandcompany.com/collections/razor-accessories\nKit https://electroandcompany.com/collections/razor-kits/products/extreme-11-000w-razor-kit?variant=48317352870186\n✅ DISCOUNT CODE \"SURRONSTER5\" ✅\n\nRazor SX500 https://amzn.to/3WuP818\nRazor MX500 https://amzn.to/3UJCIB8\n\nThrift Store 0:00\nParts and Cost 0:30\nHow to Build 2:05\nRazor vs Talaria 8:37\nPre-Ride 11:31\nTest Ride 13:03\n\nkey words: electric minibike diy electric bike how to build an electric bike how to build an electric pitbike budget electric bike tutorial cheapest electric dirt bike razor sx500 upgrade how to make razor bikes faster how to build a 72v razor how to build a razor for cheap how to make an electric bike faster how to make an electric dirtbike faster mini supermoto diy thrift store bike surronster thrift store minimoto 72v razor build tutorial electro and co razor build low cost electric dirtbike cheapest electric pit bike how to build how to build an electric stunt bike best electric bike for wheelies best electric dirtbike for wheelies"
        },
        "defaultAudioLanguage": "en-US"
      }
    },
    {
      "kind": "youtube#video",
      "etag": "nVzAgTmwWctt7kjmCeb_PWVzEmI",
      "id": "i1QZO9EiVmY",
      "snippet": {
        "publishedAt": "2024-05-09T10:00:41Z",
        "channelId": "UCyD3XWRK9ko-izf2nBSFitw",
        "title": "I Had Some Help",
        "description": "Provided to YouTube by Universal Music Group\n\nI Had Some Help · Post Malone · Morgan Wallen\n\nI Had Some Help\n\n℗ 2024 Mercury Records / Republic Records, a division of UMG Recordings, Inc.\n\nReleased on: 2024-05-10\n\nProducer, Studio  Personnel, Recording  Engineer, Vocal  Engineer: Louis Bell\nProducer: Charlie Handsome\nProducer, Co- Producer: Hoskins\nStudio  Personnel, Mixer: Ryan Gore\nAssociated  Performer, Vocals: Morgan Wallen\nAssociated  Performer, Vocals: Post Malone\nAssociated  Performer, Drums: Aaron Sterling\nAssociated  Performer, Bass: Craig Young\nAssociated  Performer, Electric  Guitar: Derek Wells\nAssociated  Performer, Acoustic  Guitar: Bryan Sutton\nAssociated  Performer, Keyboards: Dave Cohen\nAssociated  Performer, Pedal  Steel: Paul Franklin\nAssociated  Performer, Fiddle: Larry Franklin\nStudio  Personnel, Mastering  Engineer: Ted Jenson\nComposer  Lyricist: Austin Post\nComposer  Lyricist: Morgan Wallen\nComposer  Lyricist: Louis Bell\nComposer  Lyricist: Ryan Vojtesak\nComposer  Lyricist: Ernest Smith\nComposer  Lyricist: Hoskins\nComposer  Lyricist: Chandler Paul Walters\nComposer  Lyricist: Ashley Gorley\n\nAuto-generated by YouTube.",
        "thumbnails": {
          "default": {
            "url": "https://i.ytimg.com/vi/i1QZO9EiVmY/default.jpg",
            "width": 120,
            "height": 90
          },
          "medium": {
            "url": "https://i.ytimg.com/vi/i1QZO9EiVmY/mqdefault.jpg",
            "width": 320,
            "height": 180
          },
          "high": {
            "url": "https://i.ytimg.com/vi/i1QZO9EiVmY/hqdefault.jpg",
            "width": 480,
            "height": 360
          },
          "standard": {
            "url": "https://i.ytimg.com/vi/i1QZO9EiVmY/sddefault.jpg",
            "width": 640,
            "height": 480
          },
          "maxres": {
            "url": "https://i.ytimg.com/vi/i1QZO9EiVmY/maxresdefault.jpg",
            "width": 1280,
            "height": 720
          }
        },
        "channelTitle": "Post Malone - Topic",
        "tags": [
          "Post Malone",
          "ポストマローン",
          "ポスト・マローン",
          "Morgan Wallen",
          "I Had Some Help"
        ],
        "categoryId": "10",
        "liveBroadcastContent": "none",
        "localized": {
          "title": "I Had Some Help",
          "description": "Provided to YouTube by Universal Music Group\n\nI Had Some Help · Post Malone · Morgan Wallen\n\nI Had Some Help\n\n℗ 2024 Mercury Records / Republic Records, a division of UMG Recordings, Inc.\n\nReleased on: 2024-05-10\n\nProducer, Studio  Personnel, Recording  Engineer, Vocal  Engineer: Louis Bell\nProducer: Charlie Handsome\nProducer, Co- Producer: Hoskins\nStudio  Personnel, Mixer: Ryan Gore\nAssociated  Performer, Vocals: Morgan Wallen\nAssociated  Performer, Vocals: Post Malone\nAssociated  Performer, Drums: Aaron Sterling\nAssociated  Performer, Bass: Craig Young\nAssociated  Performer, Electric  Guitar: Derek Wells\nAssociated  Performer, Acoustic  Guitar: Bryan Sutton\nAssociated  Performer, Keyboards: Dave Cohen\nAssociated  Performer, Pedal  Steel: Paul Franklin\nAssociated  Performer, Fiddle: Larry Franklin\nStudio  Personnel, Mastering  Engineer: Ted Jenson\nComposer  Lyricist: Austin Post\nComposer  Lyricist: Morgan Wallen\nComposer  Lyricist: Louis Bell\nComposer  Lyricist: Ryan Vojtesak\nComposer  Lyricist: Ernest Smith\nComposer  Lyricist: Hoskins\nComposer  Lyricist: Chandler Paul Walters\nComposer  Lyricist: Ashley Gorley\n\nAuto-generated by YouTube."
        }
      }
    },
    {
      "kind": "youtube#video",
      "etag": "Xmg7KWfinEHWF52hEu5tu2gu0tw",
      "id": "EmqFoojMeD8",
      "snippet": {
        "publishedAt": "2024-05-11T18:00:06Z",
        "channelId": "UCMm211NGh4Ls5SAMZJF7E8A",
        "title": "SM64’s Unopenable Door Has Finally Been Opened!",
        "description": "I explain how Super Mario 64’s unopenable door was finally opened. If you want to support me and my efforts like this one, please consider becoming a member of my channel: https://www.youtube.com/@pannenkoek2012/join",
        "thumbnails": {
          "default": {
            "url": "https://i.ytimg.com/vi/EmqFoojMeD8/default.jpg",
            "width": 120,
            "height": 90
          },
          "medium": {
            "url": "https://i.ytimg.com/vi/EmqFoojMeD8/mqdefault.jpg",
            "width": 320,
            "height": 180
          },
          "high": {
            "url": "https://i.ytimg.com/vi/EmqFoojMeD8/hqdefault.jpg",
            "width": 480,
            "height": 360
          },
          "standard": {
            "url": "https://i.ytimg.com/vi/EmqFoojMeD8/sddefault.jpg",
            "width": 640,
            "height": 480
          },
          "maxres": {
            "url": "https://i.ytimg.com/vi/EmqFoojMeD8/maxresdefault.jpg",
            "width": 1280,
            "height": 720
          }
        },
        "channelTitle": "pannenkoek2012",
        "tags": [
          "super",
          "mario",
          "64",
          "sm64",
          "video",
          "game",
          "video game",
          "Super Mario 64 (Video Game)",
          "nintendo",
          "nintendo 64"
        ],
        "categoryId": "20",
        "liveBroadcastContent": "none",
        "localized": {
          "title": "SM64’s Unopenable Door Has Finally Been Opened!",
          "description": "I explain how Super Mario 64’s unopenable door was finally opened. If you want to support me and my efforts like this one, please consider becoming a member of my channel: https://www.youtube.com/@pannenkoek2012/join"
        },
        "defaultAudioLanguage": "en"
      }
    },
    {
      "kind": "youtube#video",
      "etag": "tCQ7jriqAsa21-1bjsMSMJkWyy8",
      "id": "7T0emrqglzA",
      "snippet": {
        "publishedAt": "2024-05-11T12:00:08Z",
        "channelId": "UCk56ama_RvUkMzexS8I9SIQ",
        "title": "I Built a Chicken Powered Murder Machine (again...)",
        "description": "This machine is fueled by two things, murder and chickens. Well, 3 if you count the power of friendship! And since this is the Lifesteal SMP, I made version 2.0 even deadlier than the last! \n\nEnjoy :)\n\nGort’s EPIC Player Launcher!:\nhttps://youtu.be/Pti_-bQYuVg?si=FZTH0EiqSZ81iTjU\n\n\nHere's Version 1.0 if you're into that sort of thing...\nhttps://www.youtube.com/watch?v=ic6aYNrxpSM&ab_channel=Branzy",
        "thumbnails": {
          "default": {
            "url": "https://i.ytimg.com/vi/7T0emrqglzA/default.jpg",
            "width": 120,
            "height": 90
          },
          "medium": {
            "url": "https://i.ytimg.com/vi/7T0emrqglzA/mqdefault.jpg",
            "width": 320,
            "height": 180
          },
          "high": {
            "url": "https://i.ytimg.com/vi/7T0emrqglzA/hqdefault.jpg",
            "width": 480,
            "height": 360
          },
          "standard": {
            "url": "https://i.ytimg.com/vi/7T0emrqglzA/sddefault.jpg",
            "width": 640,
            "height": 480
          },
          "maxres": {
            "url": "https://i.ytimg.com/vi/7T0emrqglzA/maxresdefault.jpg",
            "width": 1280,
            "height": 720
          }
        },
        "channelTitle": "Branzy",
        "categoryId": "20",
        "liveBroadcastContent": "none",
        "defaultLanguage": "en",
        "localized": {
          "title": "I Built a Chicken Powered Murder Machine (again...)",
          "description": "This machine is fueled by two things, murder and chickens. Well, 3 if you count the power of friendship! And since this is the Lifesteal SMP, I made version 2.0 even deadlier than the last! \n\nEnjoy :)\n\nGort’s EPIC Player Launcher!:\nhttps://youtu.be/Pti_-bQYuVg?si=FZTH0EiqSZ81iTjU\n\n\nHere's Version 1.0 if you're into that sort of thing...\nhttps://www.youtube.com/watch?v=ic6aYNrxpSM&ab_channel=Branzy"
        },
        "defaultAudioLanguage": "en"
      }
    },
    {
      "kind": "youtube#video",
      "etag": "LUkikcPY2-xm92XGwoU0W-b0yX8",
      "id": "GFjXfHo1oe8",
      "snippet": {
        "publishedAt": "2024-05-11T13:59:39Z",
        "channelId": "UCwpHKudUkP5tNgmMdexB3ow",
        "title": "Fatal Error! How UPS Flight 1354 Ended in Disaster",
        "description": "Get Your Exclusive NordVPN deal here ➼ https://nordvpn.com/pilot  It’s risk-free with Nord’s 30-day money-back guarantee! Every purchase of 2 years plan will receive +4 bonus months on top.\n-----------------------------------------------------\nYou knowhow sometimes, you need to make a split second decision to change a plan, only to find out that your new decision made things much worse?\n\nWell, now imagine, that this is happening to you as you are about to land a huge aircraft..\nStay tuned.\n-----------------------------------------------------\nIf you want to support the work I do on the channel, join my Patreon crew and get awesome perks and help me move the channel forward!\n👉🏻 https://www.patreon.com/mentourpilot\n\nOur Connections:\n👉🏻 Exclusive Mentour Merch: https://mentour-crew.creator-spring.com/?\n👉🏻 Our other channel: youtube.com/mentournow\n👉🏻 Amazon: https://www.amazon.com/shop/mentourpilot\n👉🏻 BOSE Aviation: https://boseaviation-emea.aero/headsets\n\nSocial:\n👉🏻 Facebook: https://www.facebook.com/MentourPilot\n👉🏻 Instagram: https://www.instagram.com/mentour_pilot\n👉🏻 Twitter: https://twitter.com/MenTourPilot\n👉🏻 Discord server: https://discord.gg/JntGWdn\n\nDownload the FREE Mentour Aviation app for all the lastest aviation content\n👉🏻 https://www.mentourpilot.com/apps/\n\nBelow you will find the links to videos and sources used in this episode.\n\nSOURCES\n-----------------------------------------------------\nFinal Report:\nhttps://www.ntsb.gov/investigations/accidentreports/reports/aar1402.pdf\n\nFull Recommendations:\nhttps://mentourpilot.com/ups-flight-1354-investigation-recommendations\n\nMicrosoft Flight Simulator 2020 add-ons:\n\niniBuilds A300-600R(F)\nhttps://inibuilds.com/products/inibuilds-a300-600r-airliner-msfs\n\nSXAIRPORTDESIGN - BIRMINGHAM-SHUTTLESWORTH\nhttps://sxairportdesign.com/kbhm-birmingham-shuttlesworth-airport/\n\nXWind Chicago Rockford (KRFD) \nhttps://inibuilds.com/products/xwind-chicago-rockford-krfd-msfs?_pos=1&_psq=KRFD&_ss=e&_v=1.0\n\nFSDT Louisville International Airport V2\nhttps://www.fsdreamteam.com/products_ksdf_msfs.html\n\nAdditional Sources: \n\nNTSB video companion to UPS 1354 accident report\nhttps://youtu.be/Dsr8C9fsYjo?si=EMADBH8qsa67vSSO\n\nFedEx Respects the Hustle of Business\nhttps://youtu.be/lF0Wi5DS8-M?si=LQX7OYp2I7yLb9m9\n\nOur 100th New Boeing 767 is Helping Save Fuel and Cut Aircraft Emissions Intensity\nhttps://youtu.be/-IRM3nST0LY?si=42cvv5ikCcPqn78P\n\nUPS Pilots Make U.S. Aviation History\nhttps://youtu.be/t_7srCasnu4?si=PfmTPKWhCY5J3BH-\n\nUPS Flight Path\nhttps://youtu.be/NPFyeu3ZZ-M?si=gPfLdbrid07HSYst\n\nThunder Over Louisville Flyby: All Female Crew (2017)\nhttps://youtu.be/WjUZ5KR94oA?si=Pq9eRtVSB8LLP5YT\n\nAMT Thanks Metro College For Career Start\nhttps://youtu.be/Lk1r7lvibjA?si=1wokbAD43dLqaaCj\n\nairBaltic Flight Dispatch on the job training\nhttps://youtu.be/DSmJ9EPCY-M?si=h5WEqg7nnlynXvKi\n\nExtra b-rolls by:\n\ncottonbro studio\nfauxels\nJack Sparrow",
        "thumbnails": {
          "default": {
            "url": "https://i.ytimg.com/vi/GFjXfHo1oe8/default.jpg",
            "width": 120,
            "height": 90
          },
          "medium": {
            "url": "https://i.ytimg.com/vi/GFjXfHo1oe8/mqdefault.jpg",
            "width": 320,
            "height": 180
          },
          "high": {
            "url": "https://i.ytimg.com/vi/GFjXfHo1oe8/hqdefault.jpg",
            "width": 480,
            "height": 360
          },
          "standard": {
            "url": "https://i.ytimg.com/vi/GFjXfHo1oe8/sddefault.jpg",
            "width": 640,
            "height": 480
          },
          "maxres": {
            "url": "https://i.ytimg.com/vi/GFjXfHo1oe8/maxresdefault.jpg",
            "width": 1280,
            "height": 720
          }
        },
        "channelTitle": "Mentour Pilot",
        "tags": [
          "true crime",
          "crime stoires",
          "storytelling",
          "mentour pilot",
          "aviation stories",
          "trending",
          "viral",
          "mentour",
          "full episode",
          "ups",
          "usa",
          "birmingham",
          "trees",
          "cargo",
          "fatigue",
          "tired",
          "sick days"
        ],
        "categoryId": "19",
        "liveBroadcastContent": "none",
        "defaultLanguage": "en-GB",
        "localized": {
          "title": "Fatal Error! How UPS Flight 1354 Ended in Disaster",
          "description": "Get Your Exclusive NordVPN deal here ➼ https://nordvpn.com/pilot  It’s risk-free with Nord’s 30-day money-back guarantee! Every purchase of 2 years plan will receive +4 bonus months on top.\n-----------------------------------------------------\nYou knowhow sometimes, you need to make a split second decision to change a plan, only to find out that your new decision made things much worse?\n\nWell, now imagine, that this is happening to you as you are about to land a huge aircraft..\nStay tuned.\n-----------------------------------------------------\nIf you want to support the work I do on the channel, join my Patreon crew and get awesome perks and help me move the channel forward!\n👉🏻 https://www.patreon.com/mentourpilot\n\nOur Connections:\n👉🏻 Exclusive Mentour Merch: https://mentour-crew.creator-spring.com/?\n👉🏻 Our other channel: youtube.com/mentournow\n👉🏻 Amazon: https://www.amazon.com/shop/mentourpilot\n👉🏻 BOSE Aviation: https://boseaviation-emea.aero/headsets\n\nSocial:\n👉🏻 Facebook: https://www.facebook.com/MentourPilot\n👉🏻 Instagram: https://www.instagram.com/mentour_pilot\n👉🏻 Twitter: https://twitter.com/MenTourPilot\n👉🏻 Discord server: https://discord.gg/JntGWdn\n\nDownload the FREE Mentour Aviation app for all the lastest aviation content\n👉🏻 https://www.mentourpilot.com/apps/\n\nBelow you will find the links to videos and sources used in this episode.\n\nSOURCES\n-----------------------------------------------------\nFinal Report:\nhttps://www.ntsb.gov/investigations/accidentreports/reports/aar1402.pdf\n\nFull Recommendations:\nhttps://mentourpilot.com/ups-flight-1354-investigation-recommendations\n\nMicrosoft Flight Simulator 2020 add-ons:\n\niniBuilds A300-600R(F)\nhttps://inibuilds.com/products/inibuilds-a300-600r-airliner-msfs\n\nSXAIRPORTDESIGN - BIRMINGHAM-SHUTTLESWORTH\nhttps://sxairportdesign.com/kbhm-birmingham-shuttlesworth-airport/\n\nXWind Chicago Rockford (KRFD) \nhttps://inibuilds.com/products/xwind-chicago-rockford-krfd-msfs?_pos=1&_psq=KRFD&_ss=e&_v=1.0\n\nFSDT Louisville International Airport V2\nhttps://www.fsdreamteam.com/products_ksdf_msfs.html\n\nAdditional Sources: \n\nNTSB video companion to UPS 1354 accident report\nhttps://youtu.be/Dsr8C9fsYjo?si=EMADBH8qsa67vSSO\n\nFedEx Respects the Hustle of Business\nhttps://youtu.be/lF0Wi5DS8-M?si=LQX7OYp2I7yLb9m9\n\nOur 100th New Boeing 767 is Helping Save Fuel and Cut Aircraft Emissions Intensity\nhttps://youtu.be/-IRM3nST0LY?si=42cvv5ikCcPqn78P\n\nUPS Pilots Make U.S. Aviation History\nhttps://youtu.be/t_7srCasnu4?si=PfmTPKWhCY5J3BH-\n\nUPS Flight Path\nhttps://youtu.be/NPFyeu3ZZ-M?si=gPfLdbrid07HSYst\n\nThunder Over Louisville Flyby: All Female Crew (2017)\nhttps://youtu.be/WjUZ5KR94oA?si=Pq9eRtVSB8LLP5YT\n\nAMT Thanks Metro College For Career Start\nhttps://youtu.be/Lk1r7lvibjA?si=1wokbAD43dLqaaCj\n\nairBaltic Flight Dispatch on the job training\nhttps://youtu.be/DSmJ9EPCY-M?si=h5WEqg7nnlynXvKi\n\nExtra b-rolls by:\n\ncottonbro studio\nfauxels\nJack Sparrow"
        },
        "defaultAudioLanguage": "en-US"
      }
    }
  ],
  "nextPageToken": "CBQQAA",
  "pageInfo": {
    "totalResults": 200,
    "resultsPerPage": 20
  }
}
